MANIFEST.in
README.rst
setup.py
KviPyTools.egg-info/PKG-INFO
KviPyTools.egg-info/SOURCES.txt
KviPyTools.egg-info/dependency_links.txt
KviPyTools.egg-info/entry_points.txt
KviPyTools.egg-info/not-zip-safe
KviPyTools.egg-info/top_level.txt
kvipytools/__init__.py
kvipytools/rename.py
kvipytools/run.py
scripts/rename.sh