Metadata-Version: 1.0
Name: KviPyTools
Version: 0.1.4
Summary: kvbik's python tools
Home-page: http://github.com/kvbik/kvipytools
Author: Jakub Vysoky
Author-email: jakub@borka.cz
License: BSD
Platform: UNKNOWN
